<?xml version="1.0" encoding="UTF-8"?>
<QCARConfig xmlns:xsi="http://www.w3.org/2001/XMLSchema-instance" xsi:noNamespaceSchemaLocation="qcar_config.xsd">
  <Tracking>
    <ImageTarget name="Watch" size="1024.000000 1024.000000" />
    <ImageTarget name="Keychain" size="1024.000000 1024.000000" />
    <ImageTarget name="Ball_Signature" size="1025.000000 1025.000000" />
    <ImageTarget name="YoguiBerra" size="1024.000000 1024.000000" />
    <ImageTarget name="ReggieJacskon" size="1024.000000 1024.000000" />
    <ImageTarget name="MarianoRivera" size="1024.000000 1024.000000" />
    <ImageTarget name="LouGehrig" size="1024.000000 1024.000000" />
    <ImageTarget name="DerekJeter" size="1024.000000 1024.000000" />
    <ImageTarget name="BabeRuth" size="1024.000000 1024.000000" />
  </Tracking>
</QCARConfig>
